LICENSE.txt
MANIFEST.in
README.md
setup.cfg
setup.py
temphelpers/__init__.py
temphelpers/managers.py
temphelpers.egg-info/PKG-INFO
temphelpers.egg-info/SOURCES.txt
temphelpers.egg-info/dependency_links.txt
temphelpers.egg-info/top_level.txt
temphelpers.egg-info/zip-safe
temphelpers/tests/__init__.py
temphelpers/tests/test_managers.py