Metadata-Version: 1.0
Name: temphelpers
Version: 1.0.0
Summary: Python library to help with using temp files and directories
Home-page: https://github.com/wtsi-hgi/python-temp-helpers
Author: Colin Nolan
Author-email: colin.nolan@sanger.ac.uk
License: MIT
Platform: UNKNOWN
